inattrails/__init__.py
inattrails/api.py
inattrails/cache.py
inattrails/gen_map.py
inattrails/inat_observation.py
inattrails/inat_place.py
inattrails/inat_status.py
inattrails/inat_taxon.py
inattrails/main.py
inattrails/read.py
inattrails/trails.py
inattrails/write_table.py
inattrails/write_waypoints.py
inattrails-0.9.11.dist-info/METADATA
inattrails-0.9.11.dist-info/WHEEL
inattrails-0.9.11.dist-info/entry_points.txt
inattrails-0.9.11.dist-info/licenses/LICENSE
inattrails-0.9.11.dist-info/RECORD
